pytetrad_plus/__init__.py
pytetrad_plus/boston_data.csv
pytetrad_plus/boston_data_raw.csv
pytetrad_plus/boston_prior.txt
pytetrad_plus/mypytetrad.py
pytetrad_plus/pytetrad_plus.py
pytetrad_plus/sub_1019.csv
pytetrad_plus-0.2.10.dist-info/METADATA
pytetrad_plus-0.2.10.dist-info/WHEEL
pytetrad_plus-0.2.10.dist-info/top_level.txt
pytetrad_plus-0.2.10.dist-info/RECORD
