Metadata-Version: 2.4
Name: pytetrad_plus
Version: 0.2.10
Summary: A package of tools for working with py-tetrad
Author-email: "Kelvin O. Lim" <lim.kelvino@gmail.com>
Project-URL: Homepage, https://github.com/kelvinlim/pytetrad_plus
Project-URL: Bug Tracker, https://github.com/kelvinlim/pytetrad_plus/issues
Classifier: Programming Language :: Python :: 3
Classifier: License :: OSI Approved :: MIT License
Classifier: Operating System :: OS Independent
Requires-Python: >=3.10
Requires-Dist: jPype1
Requires-Dist: pandas
Requires-Dist: python-dotenv
Requires-Dist: PyYAML
Requires-Dist: seaborn
Requires-Dist: semopy
Requires-Dist: graphviz
Requires-Dist: tdqm
Requires-Dist: ipykernel
Requires-Dist: dgraph_flex
Requires-Dist: ipywidgets
